bqlearn/__init__.py
bqlearn/baseline.py
bqlearn/ea.py
bqlearn/irbl.py
bqlearn/irlnl.py
bqlearn/metrics.py
bqlearn/multiclass.py
bqlearn/plugin.py
bqlearn/tradaboost.py
bqlearn/unbiased.py
bqlearn/unhinged.py
bqlearn/corruptions/__init__.py
bqlearn/corruptions/_imbalance.py
bqlearn/corruptions/_label_noise.py
bqlearn/corruptions/_sampling_biais.py
bqlearn/corruptions/_weak_labels.py
bqlearn/corruptions/noise_matrices.py
bqlearn/corruptions/tests/__init__.py
bqlearn/corruptions/tests/test_imbalance.py
bqlearn/corruptions/tests/test_label_noise.py
bqlearn/corruptions/tests/test_noise_matrices.py
bqlearn/corruptions/tests/test_sampling_biais.py
bqlearn/corruptions/tests/test_weak_labels.py
bqlearn/density_ratio/__init__.py
bqlearn/density_ratio/_idr.py
bqlearn/density_ratio/_kdr.py
bqlearn/density_ratio/_kmm.py
bqlearn/density_ratio/_pdr.py
bqlearn/density_ratio/tests/__init__.py
bqlearn/density_ratio/tests/test_dr.py
bqlearn/density_ratio/tests/test_idr.py
bqlearn/density_ratio/tests/test_kdr.py
bqlearn/density_ratio/tests/test_kmm.py
bqlearn/model_selection/__init__.py
bqlearn/model_selection/_cv.py
bqlearn/model_selection/tests/__init__.py
bqlearn/model_selection/tests/test_cv.py
bqlearn/tests/__init__.py
bqlearn/tests/test_common.py
bqlearn/tests/test_ea.py
bqlearn/tests/test_irlnl.py
bqlearn/tests/test_metrics.py
bqlearn/tests/test_multiclass.py
bqlearn/tests/test_plugin.py
bqlearn/tests/test_symmetric.py
bqlearn/tests/test_tradaboost.py
bqlearn/tests/test_unbiased.py
bqlearn/utils/__init__.py
bqlearn/utils/_categorical.py
bqlearn/utils/_sparse.py
bqlearn/utils/validation.py
bqlearn/utils/tests/__init__.py
bqlearn/utils/tests/test_categorical.py
biquality_learn-0.1.0.dist-info/LICENSE
biquality_learn-0.1.0.dist-info/METADATA
biquality_learn-0.1.0.dist-info/WHEEL
biquality_learn-0.1.0.dist-info/top_level.txt
biquality_learn-0.1.0.dist-info/RECORD
