Metadata-Version: 2.1
Name: biquality-learn
Version: 0.1.0
Summary: biquality-learn is a library à la scikit-learn for Biquality Learning.
Home-page: https://biquality-learn.readthedocs.io/
Author: Pierre Nodet
Author-email: pierre.nodet@orange.com
License: BSD 3-Clause
Project-URL: Source Code, https://github.com/biquality-learn/biquality-learn
Keywords: biquality-learn
Platform: UNKNOWN
License-File: LICENSE
Requires-Dist: joblib (>=1.1.1)
Requires-Dist: numpy (>=1.17.3)
Requires-Dist: scikit-learn (>=1.3.0)
Requires-Dist: scipy (>=1.3.2)
Requires-Dist: scs (>=3.2.2)
Requires-Dist: threadpoolctl (>=3.1.0)
Provides-Extra: tests
Requires-Dist: pytest ; extra == 'tests'
